<annotation>
    	<folder>D:\Doc\Programmation\Tensorflow_object_detection\DataSet\AquaTrash\Images</folder>
    	<filename>000013_JPG.rf.da886096a055f2b459a99d202eb3fdbf.jpg</filename>
    	<path>D:\Doc\Programmation\Tensorflow_object_detection\DataSet\AquaTrash\Images\000013_JPG.rf.da886096a055f2b459a99d202eb3fdbf.jpg</path>
    	<source>
    		<database>Unknown</database>
    	</source>
    	<size>
    		<width>3264</width>
    		<height>2448</height>
    		<depth>3</depth>
    	</size>
    	<segmented>0</segmented>
    	<object>
    		<name>plastique</name>
    		<pose>Unspecified</pose>
    		<truncated>0</truncated>
    		<difficult>0</difficult>
    		<bndbox>
    			<xmin>1016</xmin>
    			<ymin>1317</ymin>
    			<xmax>1402</xmax>
    			<ymax>1636</ymax>
    		</bndbox>
    	</object>
</annotation>